fang/__init__.py
fang/dependency_register.py
fang/di.py
fang/errors.py
fang/resolver.py
fang/resource_provider_register.py
fang-0.7.6.dist-info/DESCRIPTION.rst
fang-0.7.6.dist-info/METADATA
fang-0.7.6.dist-info/metadata.json
fang-0.7.6.dist-info/RECORD
fang-0.7.6.dist-info/top_level.txt
fang-0.7.6.dist-info/WHEEL
