Metadata-Version: 2.0
Name: fang
Version: 0.7.6
Summary: A dependency injection system for python
Home-page: https://github.com/ncraike/fang
Author: Nathan Craike
Author-email: me@ncraike.com
License: MIT
Keywords: development dependencies dependencyinjection testing
Platform: UNKNOWN
Classifier: Development Status :: 2 - Pre-Alpha
Classifier: Intended Audience :: Developers
Classifier: Topic :: Software Development
Classifier: License :: OSI Approved :: MIT License
Classifier: Programming Language :: Python :: 3
Classifier: Programming Language :: Python :: 3.4
Provides-Extra: development
Requires-Dist: pytest; extra == 'development'
Requires-Dist: pytest-cov; extra == 'development'
Requires-Dist: pytest-xdist; extra == 'development'
Provides-Extra: docs
Requires-Dist: docutils; extra == 'docs'
Requires-Dist: Pygments; extra == 'docs'
Provides-Extra: test
Requires-Dist: pytest; extra == 'test'
Requires-Dist: pytest-cov; extra == 'test'
Requires-Dist: codecov; extra == 'test'
